django_simple_comments/__init__.py
django_simple_comments/admin.py
django_simple_comments/apps.py
django_simple_comments/migrations/0001_initial.py
django_simple_comments/migrations/__init__.py
django_simple_comments/models.py
django_simple_comments/tests.py
django_simple_comments/views.py
django_simple_comments-0.1.2.dist-info/METADATA
django_simple_comments-0.1.2.dist-info/WHEEL
django_simple_comments-0.1.2.dist-info/RECORD
