Metadata-Version: 2.1
Name: django-simple-comments
Version: 0.1.2
Summary: 
Author: Akash NP
Author-email: akashnp1998@gmail.com
Requires-Python: >=3.11,<4.0
Classifier: Programming Language :: Python :: 3
Classifier: Programming Language :: Python :: 3.11
Requires-Dist: django (>=4.2.6,<5.0.0)
